mcj_text_writer/__init__.py
mcj_text_writer/server.py
mcj_text_writer-0.1.0.dist-info/METADATA
mcj_text_writer-0.1.0.dist-info/WHEEL
mcj_text_writer-0.1.0.dist-info/entry_points.txt
mcj_text_writer-0.1.0.dist-info/RECORD
